morph3dhst/__init__.py
morph3dhst-0.0.0.dist-info/METADATA
morph3dhst-0.0.0.dist-info/WHEEL
morph3dhst-0.0.0.dist-info/licenses/LICENSE
morph3dhst-0.0.0.dist-info/RECORD
